stixpy/__init__.py
stixpy/_version.py
stixpy/conftest.py
stixpy/science.py
stixpy/version.py
stixpy/_dev/__init__.py
stixpy/_dev/scm_version.py
stixpy/calibration/__init__.py
stixpy/calibration/compression.py
stixpy/calibration/detector.py
stixpy/calibration/energy.py
stixpy/calibration/grid.py
stixpy/calibration/livetime.py
stixpy/calibration/transmission.py
stixpy/calibration/visibility.py
stixpy/calibration/tests/__init__.py
stixpy/calibration/tests/test.csv
stixpy/calibration/tests/test_compression.py
stixpy/calibration/tests/test_detector.py
stixpy/calibration/tests/test_energy.py
stixpy/calibration/tests/test_grid.py
stixpy/calibration/tests/test_livetime.py
stixpy/calibration/tests/test_transmission.py
stixpy/calibration/tests/test_visibility.py
stixpy/config/__init__.py
stixpy/config/instrument.py
stixpy/config/data/.git
stixpy/config/data/.gitignore
stixpy/config/data/README.md
stixpy/config/data/detector/ScienceEnergyChannels_1000.csv
stixpy/config/data/detector/ScienceEnergyChannels_20221216.csv
stixpy/config/data/detector/ScienceEnergyChannels_20230201.csv
stixpy/config/data/detector/ScienceEnergyChannels_20230519.csv
stixpy/config/data/detector/science_echan_index.csv
stixpy/config/data/detector/stx_det_adc.csv
stixpy/config/data/detector/stx_det_pixels.csv
stixpy/config/data/detector/stx_subc_params.csv
stixpy/config/data/elut/elut_index.csv
stixpy/config/data/elut/elut_table_20200519.csv
stixpy/config/data/elut/elut_table_20201204.csv
stixpy/config/data/elut/elut_table_20210625.csv
stixpy/config/data/elut/elut_table_20211209.csv
stixpy/config/data/elut/elut_table_20220601.csv
stixpy/config/data/elut/elut_table_20220918.csv
stixpy/config/data/elut/elut_table_20221214.csv
stixpy/config/data/elut/elut_table_20221220.csv
stixpy/config/data/elut/elut_table_20230606.csv
stixpy/config/data/elut/elut_table_20230612.csv
stixpy/config/data/elut/elut_table_20230710.csv
stixpy/config/data/elut/elut_table_20231019.csv
stixpy-0.2.0.dist-info/licenses/LICENSE.rst
stixpy-0.2.0.dist-info/METADATA
stixpy-0.2.0.dist-info/WHEEL
stixpy-0.2.0.dist-info/top_level.txt
stixpy-0.2.0.dist-info/RECORD
